unitycatalog/ai/crewai/__init__.py
unitycatalog/ai/crewai/toolkit.py
unitycatalog/ai/crewai/version.py
unitycatalog_crewai-0.2.0.dist-info/METADATA
unitycatalog_crewai-0.2.0.dist-info/WHEEL
unitycatalog_crewai-0.2.0.dist-info/RECORD
