Metadata-Version: 2.4
Name: unitycatalog-crewai
Version: 0.2.0
Summary: Support for Unity Catalog functions as CrewAI tools
Author-email: Michael Berk <michaelberk99@gmail.com>
License: Apache-2.0
Requires-Python: >=3.10
Requires-Dist: crewai-tools
Requires-Dist: crewai>=0.67.1
Requires-Dist: unitycatalog-ai
Provides-Extra: databricks
Requires-Dist: unitycatalog-ai[databricks]; extra == 'databricks'
Provides-Extra: databricks-dev
Requires-Dist: unitycatalog-ai[databricks-dev]; extra == 'databricks-dev'
Provides-Extra: dev
Requires-Dist: unitycatalog-ai[dev]; extra == 'dev'
